<?xml version="1.0" encoding="utf-8" ?>
<dwsync>
<file name="ver_cajeros_generales.php" server="W:/" local="129950477273280246" remote="129950477270000000" />
<file name="mantenimiento_usuarios.php" server="W:/" local="129950477274810334" remote="129950477270000000" />
<file name="grabar_cajero_general.php" server="W:/" local="129930642514916505" remote="129930642510000000" />
<file name="definir_gerencias.php" server="W:/" local="129950477277800505" remote="129950477270000000" />
<file name="definir_departamentos.php" server="W:/" local="129950477279050576" remote="129950477270000000" />
<file name="definir_cajero_general.php" server="W:/" local="129930644119098259" remote="129930644110000000" />
<file name="definir_agencias.php" server="W:/" local="129950477281490716" remote="129950477280000000" />
<file name="cambiar_contrasenia.php" server="W:/" local="129950477283840850" remote="129950477280000000" />
<file name="definir_coordinadoras_negocio.php" server="W:/" local="129930657206786832" remote="129930657200000000" />
<file name="grabar_coordinadoras_negocio.php" server="W:/" local="129930655604825205" remote="129930655600000000" />
<file name="ver_coordinadoras_negocio.php" server="W:/" local="129950477285070920" remote="129950477280000000" />
<file name="encabezado.php" server="W:/" local="129840981565061798" remote="129840981560000000" />
<file name="pie.php" server="W:/" local="129950477194435736" remote="129950477190000000" />
<file name="configuracion.php" server="W:/" local="129930649010000000" remote="129930649010000000" />
<file name="principal.php" server="W:/" local="129950477927847685" remote="129950477920000000" />
</dwsync>